{
  "host_groups" : [
    {
      "name" : "master",
      "components" : [
      {
        "name" : "NAMENODE"
      },
      {
        "name" : "SECONDARY_NAMENODE"
      },       
      {
        "name" : "RESOURCEMANAGER"
      },
      {
        "name" : "HISTORYSERVER"
      },
      {
        "name" : "ZOOKEEPER_SERVER"
      },
      {
        "name" : "GANGLIA_SERVER"
      },
      {
        "name" : "GANGLIA_MONITOR"
      },
      {
        "name" : "APP_TIMELINE_SERVER"
      }
      ],
      "cardinality" : "1"
    },
    {
      "name" : "slave",
      "components" : [
      {
        "name" : "DATANODE"
      },
      {
        "name" : "HDFS_CLIENT"
      },
      {
        "name" : "NODEMANAGER"
      },
      {
        "name" : "YARN_CLIENT"
      },
      {
        "name" : "MAPREDUCE2_CLIENT"
      },
      {
        "name" : "ZOOKEEPER_CLIENT"
      },
      {
        "name" : "GANGLIA_MONITOR"
      }
      ],
      "cardinality" : "2"
    }
  ],
  "settings" : [{
    "recovery_settings" : [{
      "recovery_enabled" : "true"
    }
    ]}
  ],
  "Blueprints" : {
    "blueprint_name" : "blueprint",
    "stack_name" : "HDP",
    "stack_version" : "2.4"
  }
}